{"stats":{"minecraft:picked_up":{"regions_unexplored:pointed_redstone":21,"minecraft:iron_chestplate":2,"minecraft:flower_pot":2,"minecraft:anvil":2,"minecraft:smithing_table":4,"minecraft:lead":8,"minecraft:diamond_sword":13,"farmersdelight:rice_panicle":9,"mythicmobs:chupacabra_cooked_meat_skewer":2,"regions_unexplored:glistering_sprout":10,"create:item_drain":2,"minecraft:enchanted_book":4,"minecraft:brewing_stand":6,"minecraft:golden_sword":9,"bewitchment:voodoo_poppet":7,"minecraft:string":22,"bewitchment:cypress_log":8,"minecraft:red_nether_bricks":2,"bewitchment:brazier":1,"regions_unexplored:brimsprout_nylium":1,"create:water_wheel":8,"minecraft:diamond_leggings":1,"minecraft:gold_nugget":2006,"bewitchment:birch_bark":9,"minecraft:cobbled_deepslate":1626,"minecraft:spruce_planks":29,"regions_unexplored:maple_shrub":4,"bewitchment:spruce_poppet_shelf":2,"regions_unexplored:pine_shrub":1,"spectrum:radiating_ender":1,"minecraft:diamond_ore":8,"minecells:guts":10,"minecraft:sheaf_pottery_sherd":1,"farmersdelight:potato_crate":1,"minecraft:jukebox":4,"create_new_age:copper_wire":8,"bewitchment:belladonna":9,"create:andesite_casing":9,"minecraft:golden_axe":1,"regions_unexplored:raw_redstone_block":29,"minecraft:warped_button":1,"mutantmonsters:mutant_skeleton_pelvis":1,"createbigcannons:empty_machine_gun_round":12,"minecraft:black_dye":21,"create_new_age:generator_coil":2,"minecraft:stone_sword":1,"mythicmetals:raw_manganese":26,"create:copper_casing":18,"farmersdelight:onion":10,"supplementaries:quiver":1,"supplementaries:ash":5,"minecraft:blaze_rod":40,"create_dd:raw_tin":184,"minecraft:magma_block":154,"travelersbackpack:iron_golem":2,"minecraft:feather":5,"minecraft:dark_oak_boat":4,"minecraft:flint":78,"farmersdelight:carrot_crate":1,"minecraft:lantern":10,"mythicmetals:carmot_staff_smithing_template":3,"regions_unexplored:cobalt_roots":2,"lootr:trophy":3,"minecraft:twisting_vines":9,"mythicmetals:stormyx_sword":1,"botanypots:terracotta_hopper_botany_pot":2,"create:shaft":14,"minecraft:glowstone_dust":137,"mythicmetals:bronze_sword":2,"mythicmetals:raw_silver":15,"immersive_weathering:tallow":121,"patchouli:guide_book":1,"zenith:glowing_hellshelf":1,"minecraft:stripped_spruce_log":75,"minecraft:dark_oak_log":149,"minecraft:red_terracotta":24,"minecraft:barrel":3,"minecraft:bundle":3,"regions_unexplored:hyssop":1,"minecraft:blue_terracotta":33,"wilderwild:hollowed_spruce_log":1,"minecraft:lever":1,"minecraft:granite":749,"minecraft:bread":86,"bewitchment:ectoplasm":1,"bewitchment:witch_cauldron":8,"rocks:cobblestone_splitter":5,"minecraft:diamond_pickaxe":4,"minecraft:crafting_table":9,"mythicmetals:raw_palladium":25,"minecraft:coarse_dirt":11,"bewitchment:taglock":3,"minecraft:golden_pickaxe":1,"ae2:silicon_press":5,"create_new_age:layered_magnet":10,"minecraft:red_bed":1,"create:fluid_pipe":30,"bewitchment:elder_log":8,"regions_unexplored:glistering_nylium":1,"mythicmetals:raw_adamantite":5,"minecraft:beef":8,"mythicmetals:raw_midas_gold":501,"minecraft:iron_nugget":2,"mythicmetals:raw_mythril":16,"minecraft:chest":12,"minecraft:egg":2,"minecraft:copper_ore":20,"regions_unexplored:glistering_wart":2,"minecraft:stone":192,"farmersdelight:cabbage_crate":1,"farmersdelight:minced_beef":11,"minecraft:fire_charge":1,"minecraft:white_dye":1,"minecraft:redstone":1737,"create:vertical_gearbox":13,"botania:black_lotus":1,"bewitchment:juniper_sapling":14,"minecraft:hay_block":8,"minecraft:yellow_terracotta":11,"create:depot":2,"create_new_age:energiser_t1":4,"minecraft:gold_ingot":291,"minecraft:polished_blackstone":37,"regions_unexplored:purple_lupine":1,"botania:green_mystical_flower":1,"bountiful:bountyboard":1,"minecraft:white_wool":6,"extended_drawers:lock":1,"minecraft:bone_block":5,"minecraft:emerald_ore":9,"minecraft:lapis_ore":6,"minecraft:stripped_oak_log":40,"create_new_age:incomplete_wire":3,"minecraft:mud_bricks":35,"bewitchment:book_of_shadows":3,"create_dd:weathered_limestone":84,"minecraft:packed_mud":1,"minecraft:oak_log":1686,"minecraft:golden_boots":1,"farmersdelight:skillet":2,"bewitchment:aconite_seeds":23,"mutantmonsters:mutant_skeleton_limb":6,"minecraft:paper":20,"minecraft:apple":40,"minecraft:kelp":309,"bewitchment:athame":2,"minecraft:stone_pickaxe":1,"minecraft:iron_ore":5,"minecraft:cobweb":17,"regions_unexplored:cobalt_obsidian":83,"endermanoverhaul:warped_pearl":2,"minecraft:glass_bottle":11,"minecraft:iron_sword":5,"create:mechanical_saw":2,"regions_unexplored:silver_birch_sapling":3,"minecraft:smooth_basalt":4,"beautify:bookstack":9,"minecraft:sweet_berries":22,"immersive_weathering:soot":86,"minecells:monster_cell":5,"minecraft:cracked_nether_bricks":1,"minecells:infected_flesh":3,"minecraft:gravel":70,"minecraft:spruce_sapling":61,"minecraft:spruce_log":147,"create:gearbox":10,"minecraft:leather_helmet":2,"travelersbackpack:standard":3,"minecraft:coal_ore":9,"minecraft:slime_ball":6,"mythicmetals:raw_stormyx":108,"bewitchment:raw_silver":11,"create:mechanical_pump":7,"minecraft:redstone_ore":12,"mythicmetals:copper_leggings":1,"minecraft:baked_potato":1,"bewitchment:juniper_log":22,"minecells:blood_sword":1,"minecraft:hopper":2,"minecraft:ender_pearl":24,"bewitchment:juniper_broom":160,"minecraft:black_carpet":9,"zenith:infused_hellshelf":5,"minecraft:nether_brick_fence":3,"regions_unexplored:brimsprout":60,"mythicmetals:raw_kyber":2,"spectrum:citrine_block":143,"minecraft:raw_copper":836,"bewitchment:cypress_sapling":12,"mythicmetals:midas_gold_sword":1,"minecraft:experience_bottle":3,"create_new_age:overcharged_diamond":1,"create:andesite_funnel":8,"minecraft:ender_eye":7,"nethersdelight:hoglin_sirloin":41,"minecraft:iron_pickaxe":3,"create_new_age:electrical_connector":3,"minecraft:furnace":11,"minecraft:stick":225,"mythicmetals:raw_carmot":5,"create:mechanical_mixer":2,"createbigcannons:autocannon_cartridge_sheet":3,"create_enchantment_industry:disenchanter":2,"minecraft:torch":42,"minecraft:porkchop":34,"minecraft:diorite":473,"minecraft:music_disc_pigstep":1,"mythicmetals:morkite":189,"ae2:sky_stone_block":64,"bewitchment:white_coffin":3,"create:large_cogwheel":2,"bewitchment:snake_tongue":9,"minecraft:quartz_block":1,"farmersdelight:tomato_crate":2,"minecraft:rotten_flesh":93,"regions_unexplored:tsubaki":1,"mythicmetals:stormyx_pickaxe":1,"minecells:elevator_assembler":6,"bewitchment:stripped_elder_log":5,"bewitchment:mandrake_root":30,"mutantmonsters:mutant_skeleton_shoulder_pad":2,"bewitchment:golden_chalk":1,"minecraft:obsidian":56,"mythicmetals:copper_chestplate":1,"minecraft:cod":1,"farmersdelight:beetroot_crate":1,"minecraft:blaze_powder":1,"minecraft:cobblestone":4711,"minecraft:enchanting_table":5,"minecraft:leather_chestplate":3,"farmersdelight:onion_crate":1,"minecraft:magma_cream":13,"create:fluid_tank":1,"minecraft:andesite":190,"minecraft:potato":4,"create:belt_connector":2,"minecraft:tuff":32,"create:raw_zinc":158,"minecraft:prismarine_bricks":127,"minecraft:wither_skeleton_skull":8,"zenith:filtering_shelf":1,"minecraft:lapis_lazuli":248,"minecraft:dirt":456,"minecraft:stripped_birch_log":29,"culturaldelights:glow_squid":3,"minecraft:leather_boots":7,"minecraft:bone":147,"farmersdelight:iron_knife":3,"minecraft:bow":5,"minecraft:wheat_seeds":71,"minecraft:raw_gold":153,"create_new_age:magnetite_block":29,"bewitchment:stripped_cypress_log":2,"minecraft:light_blue_dye":1,"minecraft:grindstone":1,"ae2:logic_processor_press":5,"minecraft:bamboo":29,"minecraft:oak_planks":4,"botania:gray_mystical_flower":2,"extended_drawers:single_drawer":22,"minecraft:ghast_tear":8,"create:cogwheel":4,"goodending:spicy_wildflowers":62,"minecraft:sand":17,"design_decor:cardboard_box":13,"endermanoverhaul:soul_pearl":4,"mythicmetals:raw_quadrillum":24,"minecraft:grass_block":3,"minecraft:lily_of_the_valley":11,"minecraft:mossy_cobblestone":24,"regions_unexplored:cattail":2,"minecraft:diamond":39,"minecraft:spruce_boat":31,"minecraft:soul_lantern":5,"regions_unexplored:brimwood_leaves":1,"minecraft:bone_meal":2,"alloy_forgery:polished_blackstone_forge_controller":2,"farmersdelight:rice_bag":1,"minecraft:emerald":76,"minecraft:oak_sapling":81,"minecraft:netherrack":781,"nethersdelight:hoglin_loin":28,"minecraft:charcoal":53,"minecraft:mud_brick_slab":4,"create_new_age:thorium":114,"minecraft:allium":29,"minecraft:brown_mushroom":16,"create:rotation_speed_controller":2,"minecraft:gold_block":16,"create:schematic_table":1,"minecraft:chain":72,"minecraft:brick":4,"minecraft:shield":1,"minecraft:moss_carpet":2,"create_new_age:overcharged_golden_wire":6,"minecraft:item_frame":5,"botania:magenta_mystical_flower":2,"minecraft:blackstone":5,"minecraft:blue_orchid":1,"mythicmetals:copper_sword":1,"mythicmobs:chupacabra_raw_meat":1,"minecraft:candle":4,"create:zinc_ore":8,"create:basin":1,"minecraft:lectern":14,"minecraft:sugar_cane":313,"minecraft:dark_oak_sapling":1,"minecraft:raw_iron":115,"regions_unexplored:silver_birch_leaf_pile":3,"minecraft:copper_ingot":1,"extended_drawers:t2_upgrade":3,"minecraft:bowl":11,"zenith:deepshelf":2,"regions_unexplored:blue_lupine":1,"minecraft:polished_blackstone_bricks":6,"create:hand_crank":2,"minecraft:dark_oak_planks":2,"bewitchment:stripped_juniper_log":6,"zenith:seashelf":24,"minecraft:arrow":135,"bewitchment:garlic":20,"regions_unexplored:redstone_bulb":2,"regions_unexplored:maple_sapling":1,"minecraft:nether_bricks":22,"mutantmonsters:mutant_skeleton_rib":4,"minecraft:saddle":2,"ae2:calculation_processor_press":5,"create_dd:hydraulic_scaffolding":2,"regions_unexplored:peat_dirt":20,"regions_unexplored:dorcel":2,"regions_unexplored:glistering_fern":1,"minecraft:basalt":68,"immersive_weathering:spruce_bark":7,"minecraft:glow_ink_sac":1,"immersive_weathering:moss_clump":10,"mythicmetals:raw_banglum":28,"bewitchment:voodoo_protection_poppet":3,"minecraft:leather":59,"minecraft:birch_planks":27,"minecraft:yellow_glazed_terracotta":20,"minecraft:gunpowder":28,"minecraft:cobblestone_stairs":1,"bewitchment:stone_witch_altar":9,"bewitchment:wood_ash":18,"bewitchment:elder_sapling":4,"minecraft:red_nether_brick_stairs":5,"create_dd:potassic":246,"bewitchment:chalk":1,"bewitchment:aconite":18,"bewitchment:mandrake_seeds":17,"minecraft:iron_ingot":45,"zenith:hellshelf":30,"bewitchment:demon_horn":17,"minecraft:soul_sand":2,"minecraft:book":103,"minecraft:warped_fungus":6,"create_new_age:energiser_t2":1,"minecraft:quartz":1707,"bewitchment:belladonna_seeds":6,"bewitchment:salt":73,"bewitchment:demon_heart":4,"minecraft:white_bed":15,"minecraft:gold_ore":6,"minecraft:spider_eye":5,"regions_unexplored:silver_birch_log":18,"minecraft:iron_helmet":2,"regions_unexplored:maple_log":24,"ae2:engineering_processor_press":5,"minecraft:damaged_anvil":3,"minecraft:coal":534},"minecraft:killed":{"naturalist:boar":8,"minecraft:skeleton":73,"minecells:grenadier":1,"minecraft:magma_cube":34,"minecraft:pillager":2,"minecraft:zombie":40,"minecells:shieldbearer":2,"minecraft:cow":1,"minecraft:vindicator":1,"minecells:undead_archer":3,"bewitchment:hellhound":7,"naturalist:bear":1,"endermanoverhaul:warped_forest_enderman":5,"minecraft:wandering_trader":4,"minecraft:enderman":7,"minecraft:zombified_piglin":67,"minecraft:witch":2,"minecraft:spider":10,"minecraft:silverfish":2,"minecells:leaping_zombie":4,"minecraft:piglin_brute":1,"minecraft:piglin":23,"minecraft:creeper":4,"minecraft:trader_llama":10,"minecraft:ghast":10,"minecraft:blaze":18,"minecraft:slime":8,"bewitchment:ghost":2,"minecraft:phantom":1,"endermanoverhaul:soulsand_valley_enderman":3,"mythicmobs:chupacabra":2,"minecraft:drowned":2,"naturalist:bluejay":2,"creeperoverhaul:spruce_creeper":1,"minecraft:bat":1,"minecraft:hoglin":17,"endermanoverhaul:spirit":9,"mutantmonsters:mutant_enderman":3,"minecraft:wither_skeleton":25,"minecraft:player":1,"bewitchment:demon":1},"minecraft:mined":{"minecraft:dark_oak_planks":2,"farmersdelight:rice_bag":1,"minecraft:white_bed":15,"create:copper_casing":18,"regions_unexplored:brimsprout":4,"regions_unexplored:blue_lupine":1,"bewitchment:spruce_poppet_shelf":2,"create:andesite_casing":9,"minecraft:red_nether_bricks":2,"minecraft:obsidian":43,"regions_unexplored:brimwood_leaves":3,"mythicmetals:deepslate_morkite_ore":26,"regions_unexplored:cattail":2,"minecraft:granite":515,"universal_ores:tuff_gold_ore":4,"mythicmetals:deepslate_adamantite_ore":3,"zenith:glowing_hellshelf":1,"minecraft:hopper":2,"create:rotation_speed_controller":2,"universal_ores:diorite_copper_ore":5,"minecraft:tall_seagrass":1,"minecraft:polished_blackstone_bricks":6,"regions_unexplored:stone_bud":76,"minecraft:magma_block":210,"regions_unexplored:pointed_redstone":10,"immersive_weathering:mossy_stone":14,"minecraft:barrel":2,"minecraft:fire":52,"create:encased_fluid_pipe":3,"mythicmetals:stormyx_ore":57,"minecraft:enchanting_table":4,"minecraft:twisting_vines":6,"amendments:wall_lantern":1,"bewitchment:elder_log":8,"create:item_drain":2,"botania:green_mystical_flower":1,"create_dd:weathered_limestone":64,"create:cogwheel":1,"botanypots:terracotta_hopper_botany_pot":2,"minecraft:red_bed":1,"minecraft:kelp_plant":76,"immersive_weathering:spruce_leaf_pile":203,"immersive_weathering:regions_unexplored/silver_birch_leaf_pile":12,"farmersdelight:potato_crate":1,"design_decor:cardboard_box":11,"minecraft:torch":17,"farmersdelight:cabbage_crate":1,"regions_unexplored:peat_grass_block":7,"mythicmetals:deepslate_carmot_ore":2,"minecraft:damaged_anvil":2,"minecraft:sugar_cane":39,"bewitchment:belladonna":2,"minecraft:chain":47,"minecraft:wheat":8,"universal_ores:diorite_coal_ore":11,"minecraft:jukebox":3,"minecraft:yellow_glazed_terracotta":20,"minecraft:grass":136,"create:hand_crank":1,"minecraft:smooth_basalt":2,"minecraft:deepslate":763,"create:zinc_ore":32,"regions_unexplored:glistering_sprout":7,"universal_ores:blackstone_quartz_ore":3,"minecraft:yellow_terracotta":11,"minecraft:suspicious_gravel":2,"minecraft:mossy_cobblestone":4,"minecraft:stripped_birch_log":29,"minecraft:dark_oak_log":1,"create:fluid_tank":1,"minecraft:nether_bricks":9,"minecraft:allium":8,"mythicmetals:silver_ore":10,"create_new_age:thorium_ore":42,"bewitchment:silver_ore":2,"create_new_age:energiser_t2":1,"minecraft:kelp":16,"bewitchment:deepslate_silver_ore":3,"farmersdelight:wild_onions":10,"minecraft:redstone_ore":22,"botania:magenta_mystical_flower":2,"create:shaft":9,"mythicmetals:quadrillum_ore":5,"minecraft:packed_mud":1,"universal_ores:granite_coal_ore":7,"mythicmetals:kyber_ore":1,"bewitchment:black_stone_witch_altar":6,"zenith:seashelf":24,"immersive_weathering:charred_log":1,"minecraft:andesite":156,"mythicmetals:deepslate_mythril_ore":11,"create_new_age:layered_magnet":10,"alloy_forgery:polished_blackstone_forge_controller":2,"spectrum:deepslate_shimmerstone_ore":1,"minecraft:bamboo":29,"create:andesite_encased_large_cogwheel":1,"minecells:alchemy_equipment_1":1,"minecraft:white_wool":6,"minecraft:smithing_table":2,"minecraft:mud_brick_slab":4,"create_dd:deepslate_tin_ore":22,"minecraft:soul_sand":1,"minecraft:lily_of_the_valley":7,"create_new_age:magnetite_block":25,"create:fluid_pipe":20,"bewitchment:aconite":5,"create:mechanical_pump":7,"minecraft:emerald_ore":9,"bewitchment:garlic":5,"minecraft:copper_ore":110,"minecraft:tall_grass":5,"minecraft:deepslate_gold_ore":36,"minecraft:diorite":314,"bewitchment:mandrake":1,"create:mechanical_saw":3,"minecraft:red_terracotta":24,"farmersdelight:skillet":2,"minecraft:coarse_dirt":5,"create:gearbox":2,"minecraft:spruce_log":146,"regions_unexplored:silver_birch_log":18,"minecraft:gravel":140,"create_dd:potassic":249,"minecraft:cobweb":3,"botania:gray_mystical_flower":2,"regions_unexplored:glistering_wart":2,"minecraft:polished_blackstone":37,"minecraft:gold_ore":15,"universal_ores:tuff_iron_ore":4,"minecraft:infested_stone":3,"regions_unexplored:tassel":1,"minecraft:fern":1,"create:deepslate_zinc_ore":11,"minecraft:spruce_planks":7,"mythicmetals:midas_gold_ore":123,"minecraft:oak_sapling":1,"regions_unexplored:maple_log":23,"universal_ores:granite_copper_ore":6,"bewitchment:cypress_sapling":2,"farmersdelight:tomato_crate":2,"minecraft:brewing_stand":4,"travelersbackpack:iron_golem":2,"zenith:filtering_shelf":1,"minecraft:grass_block":16,"regions_unexplored:pine_shrub":1,"minecraft:mud_bricks":35,"create_new_age:electrical_connector":3,"mythicmetals:palladium_ore":9,"minecraft:glowstone":40,"universal_ores:andesite_coal_ore":8,"minecraft:red_nether_brick_stairs":1,"minecraft:iron_ore":16,"minecraft:anvil":2,"universal_ores:andesite_diamond_ore":1,"regions_unexplored:dorcel":1,"bountiful:bountyboard":1,"minecraft:deepslate_redstone_ore":212,"minecraft:blackstone":3,"minecraft:twisting_vines_plant":5,"zenith:infused_hellshelf":5,"minecraft:soul_lantern":1,"minecraft:chest":3,"minecraft:cobblestone":225,"minecraft:nether_quartz_ore":864,"minecraft:grindstone":1,"minecraft:wall_torch":11,"bewitchment:witch_cauldron":9,"minecraft:deepslate_copper_ore":6,"minecraft:seagrass":1,"minecraft:blue_terracotta":33,"bewitchment:brazier":1,"lootr:trophy":2,"mythicmetals:manganese_ore":7,"minecraft:oak_log":6,"bewitchment:white_coffin":3,"zenith:deepshelf":2,"regions_unexplored:peat_dirt":8,"minecraft:dirt":347,"minecraft:sand":17,"mythicmetals:morkite_ore":5,"regions_unexplored:cobalt_nylium":1,"universal_ores:basalt_quartz_ore":29,"minecraft:netherrack":626,"regions_unexplored:glistering_nylium":1,"regions_unexplored:cobalt_obsidian":83,"create:andesite_encased_cogwheel":1,"minecraft:nether_gold_ore":298,"minecraft:diamond_ore":9,"minecraft:tuff":30,"create_new_age:energiser_t1":4,"minecraft:candle":1,"minecraft:deepslate_diamond_ore":4,"bewitchment:juniper_sapling":1,"immersive_weathering:regions_unexplored/maple_leaf_pile":26,"universal_ores:andesite_redstone_ore":6,"minecraft:glow_lichen":1,"minecraft:lever":1,"bewitchment:stripped_elder_log":5,"create:large_cogwheel":1,"bewitchment:juniper_log":22,"create:depot":2,"minecells:elevator_assembler":6,"immersive_weathering:regions_unexplored/larch_leaf_pile":1,"immersive_weathering:bewitchment/elder_leaf_pile":2,"minecraft:spruce_leaves":39,"rocks:rock":2,"regions_unexplored:raw_redstone_block":16,"minecraft:large_fern":3,"minecraft:hay_block":5,"minecraft:spruce_sapling":1,"zenith:hellshelf":30,"minecraft:furnace":6,"minecraft:stripped_spruce_log":75,"minecraft:gold_block":16,"minecraft:nether_brick_fence":2,"minecraft:bookshelf":33,"minecraft:deepslate_iron_ore":28,"bewitchment:salt_ore":46,"mythicmetals:nether_banglum_ore":4,"minecraft:stripped_oak_log":40,"regions_unexplored:medium_grass":138,"minecraft:stone":4252,"universal_ores:andesite_copper_ore":30,"regions_unexplored:brimsprout_nylium":2,"regions_unexplored:redstone_bulb":1,"supplementaries:book_pile_horizontal":3,"beautify:bookstack":9,"mythicmetals:platinum_ore":1,"regions_unexplored:silver_birch_leaf_pile":1,"minecraft:basalt":68,"extended_drawers:single_drawer":22,"travelersbackpack:standard":3,"universal_ores:granite_lapis_ore":8,"bewitchment:stripped_juniper_log":6,"minecraft:crafting_table":6,"immersive_weathering:soot":8,"minecraft:lectern":14,"farmersdelight:onion_crate":1,"farmersdelight:carrot_crate":1,"minecells:alchemy_equipment_0":2,"minecraft:lapis_ore":8,"bewitchment:stripped_cypress_log":2,"supplementaries:urn":4,"minecraft:prismarine_bricks":121,"create:schematic_table":1,"minecraft:birch_planks":27,"create_enchantment_industry:disenchanter":3,"bewitchment:elder_leaves":133,"regions_unexplored:redstone_bud":55,"minecraft:sweet_berry_bush":3,"bewitchment:cypress_log":8,"immersive_weathering:bewitchment/juniper_leaf_pile":59,"minecraft:coal_ore":258,"create_new_age:generator_coil":2,"minecraft:flower_pot":1,"immersive_weathering:bewitchment/cypress_leaf_pile":18,"regions_unexplored:glistering_ivy_plant":1,"create:andesite_encased_shaft":5,"regions_unexplored:maple_shrub":4,"farmersdelight:beetroot_crate":1,"mythicmetals:banglum_ore":8,"create_dd:tin_ore":82},"minecraft:custom":{"minecraft:interact_with_crafting_table":234,"minecraft:open_barrel":92,"minecraft:leave_game":30,"minecraft:time_since_death":335770,"minecraft:damage_blocked_by_shield":570,"minecraft:play_time":1544865,"minecraft:deaths":14,"minecraft:jump":17494,"minecraft:enchant_item":46,"minecraft:interact_with_furnace":232,"minecraft:traded_with_villager":132,"minecraft:interact_with_cartography_table":1,"minecraft:sleep_in_bed":14,"minecraft:damage_dealt":79513,"minecraft:open_diamond_chest":182,"minecraft:interact_with_smithing_table":30,"minecraft:interact_with_anvil":9,"minecraft:inspect_hopper":23,"minecraft:sneak_time":30792,"minecraft:total_world_time":1544865,"minecraft:items_extracted":1084,"minecraft:time_since_rest":40968,"minecraft:swim_one_cm":492745,"minecraft:fly_one_cm":3450592,"minecraft:open_chest":733,"minecraft:open_iron_chest":556,"minecraft:fall_one_cm":557105,"lootr:looted_stat":134,"minecraft:damage_resisted":0,"minecraft:sprint_one_cm":2612648,"minecraft:drop":435,"minecraft:talked_to_villager":127,"minecraft:interact_with_brewingstand":24,"minecraft:walk_on_water_one_cm":72808,"minecraft:player_kills":1,"minecraft:crouch_one_cm":72593,"minecraft:open_copper_barrel":24,"minecraft:mob_kills":434,"minecraft:items_inserted":1651,"minecraft:damage_dealt_resisted":0,"minecraft:climb_one_cm":8801,"minecraft:walk_one_cm":2371254,"minecraft:walk_under_water_one_cm":63068,"minecraft:boat_one_cm":713121,"minecraft:interact_with_grindstone":14,"minecraft:damage_taken":19442},"minecraft:crafted":{"mythicmetals:orichalcum_chestplate":1,"minecraft:black_dye":57,"minecraft:smooth_stone":3,"travelersbackpack:crafting_upgrade":1,"botanypots:terracotta_hopper_botany_pot":2,"regions_unexplored:maple_planks":24,"minecraft:blaze_powder":4,"minecraft:chain":143,"bewitchment:voodoo_protection_poppet":9,"minecraft:birch_slab":12,"minecraft:lever":2,"mythicmetals:stormyx_boots":2,"minecraft:bookshelf":50,"mythicmetals:midas_gold_chestplate":1,"create:vertical_gearbox":1,"minecraft:glass":16,"minecraft:quartz_block":352,"minecraft:diamond_helmet":4,"explorerscompass:explorerscompass":1,"minecraft:dried_kelp_block":18,"bewitchment:witch_cauldron":2,"create:cogwheel":14,"mythicmetals:midas_gold_helmet":1,"minecraft:flower_pot":1,"minecraft:glass_bottle":36,"minecraft:emerald":128,"minecraft:cooked_porkchop":30,"minecraft:diamond_axe":2,"mythicmetals:midas_gold_ingot":2,"minecraft:hay_block":1,"farmersdelight:beef_patty":23,"create:clutch":1,"zenith:glowing_hellshelf":6,"create:gearbox":1,"extended_drawers:upgrade_frame":24,"minecraft:lectern":1,"naturescompass:naturescompass":1,"bewitchment:juniper_broom":3,"mythicmetals:stormyx_leggings":2,"minecraft:iron_pickaxe":1,"minecraft:iron_block":15,"extended_drawers:lock":2,"minecraft:gold_ingot":301,"zenith:weapon_tome":4,"zenith:hellshelf":10,"minecraft:stone_shovel":1,"minecraft:iron_nugget":252,"minecells:elevator_mechanism":4,"zenith:treasure_shelf":1,"minecraft:bone_meal":165,"mythicmetals:midas_folding_template":202,"travelersbackpack:blank_upgrade":4,"travelersbackpack:gold_tier_upgrade":1,"bewitchment:stone_witch_altar":3,"minecraft:terracotta":1,"minecraft:diamond":27,"minecraft:spruce_slab":18,"minecraft:stone_pickaxe":2,"create_new_age:generator_coil":1,"extended_drawers:t1_upgrade":12,"minecraft:spruce_boat":2,"minecraft:redstone_block":163,"minecraft:dark_oak_planks":512,"handcrafted:black_sheet":8,"bewitchment:book_of_shadows":2,"mythicmetals:stormyx_chestplate":2,"minecraft:coal_block":21,"minecraft:pufferfish":6,"farmersdelight:cooked_mutton_chops":2,"bewitchment:athame":1,"minecraft:enchanting_table":1,"minecraft:dried_kelp":329,"create:andesite_alloy_block":1,"minecraft:glowstone":32,"minecraft:enchanted_book":1,"bewitchment:golden_chalk":1,"extended_drawers:single_drawer":5,"create:raw_zinc":81,"minecraft:wooden_axe":1,"minecraft:white_bed":1,"mythicmetals:midas_gold_leggings":1,"create:shaft":24,"create_new_age:energiser_t3":1,"minecraft:brick":9,"minecraft:oak_planks":1808,"minecraft:barrel":18,"bewitchment:spruce_poppet_shelf":1,"minecraft:lightning_rod":5,"minecraft:stone":6,"mythicmetals:midas_gold_nugget":810,"minecraft:hopper":3,"minecraft:bow":4,"mythicmetals:raw_silver":18,"minecraft:comparator":4,"design_decor:cardboard_box":2,"create_new_age:energiser_t1":1,"minecraft:chest":12,"minecraft:copper_block":1,"minecraft:stone_hoe":2,"minecraft:oak_slab":48,"create:depot":2,"travelersbackpack:iron_tier_upgrade":1,"minecraft:cauldron":2,"minecraft:crafting_table":5,"minecraft:spruce_planks":298,"beautify:bookstack":5,"minecraft:baked_potato":56,"create:fluid_pipe":16,"create_new_age:fluxuated_magnetite":10,"mythicmetals:midas_gold_block":97,"bewitchment:juniper_planks":24,"minecraft:brush":1,"mythicmetals:bronze_boots":1,"zenith:scrap_tome":8,"create:zinc_nugget":324,"mythicmetals:midas_gold_sword":68,"create_new_age:electrical_connector":4,"create:sand_paper":2,"minecraft:gold_block":49,"minecraft:brewing_stand":1,"minecraft:birch_planks":136,"mythicmetals:bronze_leggings":1,"mythicmetals:bronze_sword":1,"minecraft:prismarine_brick_slab":6,"minecraft:book":32,"minecraft:paper":72,"minecraft:diamond_pickaxe":4,"minecraft:emerald_block":1,"minecraft:stick":4288,"mythicmetals:stormyx_helmet":2,"create:mechanical_pump":2,"minecraft:iron_ingot":204,"minecraft:redstone_torch":12,"bewitchment:voodoo_poppet":2,"mythicmetals:bronze_helmet":1,"design_decor:cardboard_sheet":8,"bewitchment:white_coffin":1,"minecraft:furnace":1,"minecraft:raw_copper_block":11,"minecraft:flint_and_steel":1,"mythicmetals:midas_gold_boots":1,"minecraft:iron_axe":1,"bewitchment:cypress_planks":8,"create:fluid_tank":6,"mythicmetals:bronze_pickaxe":2,"create:filter":1,"bewitchment:waystone":1,"travelersbackpack:diamond_tier_upgrade":1,"create:andesite_alloy":128,"minecraft:diamond_sword":1,"create_enchantment_industry:disenchanter":2,"extended_drawers:t2_upgrade":6,"bewitchment:chalk":3,"minecraft:iron_sword":2,"minecraft:bowl":48,"bewitchment:taglock":19,"minecraft:nether_bricks":64,"mythicmetals:bronze_axe":1,"minecraft:bucket":1,"create_new_age:energiser_t2":2,"zenith:filtering_shelf":1,"minecraft:air":0,"zenith:seashelf":6,"minecraft:gold_nugget":18,"minecells:elevator_assembler":4,"minecraft:black_carpet":3,"minecraft:anvil":1,"minecraft:torch":124,"mythicmetals:bronze_chestplate":1,"minecraft:clay":6,"minecraft:lapis_block":16},"minecraft:killed_by":{"minecraft:magma_cube":1,"mutantmonsters:mutant_enderman":1,"minecells:leaping_zombie":1,"endermanoverhaul:swamp_enderman":1,"minecraft:creeper":1,"endermanoverhaul:soulsand_valley_enderman":1,"minecraft:skeleton":1},"minecraft:dropped":{"bewitchment:juniper_bark":2,"farmersdelight:iron_knife":3,"minecraft:iron_sword":2,"bewitchment:chalk":2,"minecraft:glass_bottle":21,"minecraft:diamond":11,"minecraft:crafting_table":3,"createbigcannons:autocannon_cartridge_sheet":3,"zenith:improved_scrap_tome":4,"create:cogwheel":1,"bewitchment:aconite":5,"minecraft:saddle":2,"minecraft:leather_helmet":2,"bewitchment:aconite_seeds":4,"minecraft:emerald":23,"minecraft:dirt":3,"minecraft:chain":50,"minecraft:gold_nugget":12,"minecraft:bone_block":5,"minecraft:iron_pickaxe":5,"regions_unexplored:redstone_bulb":1,"minecraft:lever":1,"bewitchment:salt":1,"minecraft:iron_nugget":20,"minecraft:cobbled_deepslate":562,"minecraft:black_carpet":3,"mythicmetals:copper_boots":1,"minecraft:obsidian":4,"minecraft:rotten_flesh":5,"minecraft:oak_planks":4,"minecraft:nether_brick_fence":1,"minecraft:charcoal":78,"minecraft:leather_boots":7,"bewitchment:spruce_bark":1,"botania:black_lotus":1,"bewitchment:stone_witch_altar":2,"create:mechanical_mixer":1,"minecraft:iron_ingot":11,"minecraft:enchanted_book":8,"minecraft:golden_boots":1,"minecraft:black_dye":21,"minecraft:wheat_seeds":11,"minecraft:feather":2,"minecraft:cobblestone":256,"minecraft:book":1,"minecraft:apple":11,"mythicmobs:chupacabra_cooked_meat_skewer":1,"minecraft:granite":283,"bewitchment:snake_tongue":4,"minecraft:music_disc_pigstep":1,"bewitchment:book_of_shadows":4,"minecraft:coal":2,"minecraft:cobweb":20,"minecraft:golden_carrot":2,"create_dd:hydraulic_scaffolding":2,"regions_unexplored:purple_lupine":1,"minecraft:potion":1,"minecraft:dried_kelp":2,"minecraft:smooth_stone":2,"bewitchment:athame":2,"minecraft:paper":20,"minecraft:string":8,"create:raw_zinc":9,"minecraft:furnace":5,"minecraft:moss_carpet":1,"spectrum:citrine_block":143,"minecraft:stone_sword":1,"minecraft:experience_bottle":3,"minecraft:damaged_anvil":1,"create:copper_sheet":5,"minecraft:nether_bricks":13,"minecells:monster_cell":1,"minecraft:diamond_sword":2,"minecraft:hay_block":3,"minecraft:stone":65,"bewitchment:mandrake_seeds":2,"create_new_age:magnetite_block":5,"minecraft:spruce_planks":22,"minecraft:bundle":1,"minecraft:diamond_pickaxe":4,"mythicmetals:copper_chestplate":1,"minecells:guts":7,"minecraft:spider_eye":2,"minecraft:warped_button":1,"minecraft:bow":1,"bewitchment:voodoo_poppet":7,"create:andesite_funnel":4,"create:belt_connector":1,"bewitchment:demon_horn":4,"minecraft:soul_sand":1,"beautify:bookstack":5,"minecraft:oak_log":968,"minecraft:baked_potato":1,"minecraft:golden_pickaxe":1,"minecraft:ender_pearl":1,"minecraft:lantern":7,"minecells:blood_sword":1,"minecraft:leather":11,"bewitchment:elder_sapling":1,"minecraft:cod":4,"minecraft:flint":8,"rocks:cobblestone_splitter":2,"minecraft:dark_oak_log":99,"regions_unexplored:brimsprout":6,"mythicmetals:stormyx_sword":1,"regions_unexplored:pointed_redstone":12,"ae2:silicon_press":5,"zenith:scrap_tome":7,"minecraft:gold_ingot":282,"ae2:engineering_processor_press":5,"ae2:calculation_processor_press":5,"lootr:trophy":1,"goodending:spicy_wildflowers":6,"regions_unexplored:raw_redstone_block":13,"bountiful:bounty":1,"minecraft:blackstone":1,"mythicmetals:raw_quadrillum":12,"minecraft:soul_lantern":1,"bewitchment:birch_bark":9,"bewitchment:belladonna":5,"minecraft:leather_chestplate":3,"minecraft:gunpowder":1,"create_dd:weathered_limestone":20,"create:gearbox":5,"bewitchment:golden_chalk":1,"mythicmetals:midas_gold_sword":1,"minecraft:glowstone":14,"minecraft:chest":4,"immersive_weathering:moss_clump":5,"minecraft:prismarine_bricks":6,"minecraft:cracked_nether_bricks":1,"minecraft:quartz":484,"create_new_age:incomplete_wire":2,"minecraft:netherrack":8,"minecraft:enchanting_table":1,"bewitchment:taglock":4,"immersive_weathering:soot":19,"minecraft:bread":86,"minecraft:mossy_cobblestone":1,"minecraft:smithing_table":2,"mythicmetals:morkite":44,"extended_drawers:t2_upgrade":3,"ae2:sky_stone_block":64,"minecraft:golden_axe":1,"bewitchment:elder_bark":1,"mythicmetals:copper_leggings":1,"minecraft:copper_ingot":2,"minecraft:stick":49,"bewitchment:mandrake_root":6,"minecraft:diorite":197,"minecraft:brewing_stand":2,"bewitchment:garlic":1,"design_decor:cardboard_box":2,"minecraft:smooth_basalt":2,"minecraft:redstone":45,"nethersdelight:hoglin_sirloin":9,"minecraft:kelp":1,"minecraft:sweet_berries":13,"minecraft:coarse_dirt":1,"minecraft:jukebox":1,"create_new_age:overcharged_diamond":2,"mythicmetals:carmot_staff_smithing_template":3,"minecraft:raw_iron":16,"minecraft:wither_skeleton_skull":1,"ae2:logic_processor_press":5,"minecraft:red_nether_brick_stairs":4,"create_new_age:overcharged_golden_sheet":1,"mythicmetals:stormyx_pickaxe":1,"mythicmetals:bronze_sword":2,"minecraft:golden_sword":9,"minecells:health_flask":1,"minecraft:raw_gold":43,"minecraft:brick":4},"minecraft:broken":{"mythicmetals:bronze_pickaxe":2,"mythicmetals:bronze_boots":1,"mythicmetals:bronze_leggings":1,"minecraft:diamond_pickaxe":1,"minecraft:leather_helmet":1,"mythicmetals:stormyx_helmet":1,"minecraft:shield":1,"minecraft:iron_axe":1,"minecraft:iron_pickaxe":2,"mythicmetals:bronze_helmet":1,"mythicmetals:bronze_chestplate":1,"minecraft:stone_pickaxe":3,"mythicmetals:stormyx_boots":1,"mythicmetals:bronze_sword":1},"minecraft:used":{"minecraft:nether_brick_fence":2,"minecraft:polished_blackstone":37,"minecraft:chest":11,"bewitchment:stripped_elder_log":1,"lootr:trophy":3,"minecraft:red_nether_brick_stairs":1,"minecraft:stone":137,"minecraft:rotten_flesh":3,"create:fluid_tank":7,"minecraft:lily_of_the_valley":11,"create_new_age:overcharged_golden_wire":7,"create:depot":4,"regions_unexplored:silver_birch_sapling":3,"minecraft:spruce_boat":31,"minecraft:copper_ore":12,"create_new_age:magnetite_block":1,"regions_unexplored:silver_birch_leaf_pile":3,"create:zinc_ore":6,"minecraft:dark_oak_boat":4,"minecraft:bow":151,"create:rotation_speed_controller":2,"minecraft:furnace":7,"create:shaft":17,"mythicmetals:orichalcum_chestplate":1,"minecraft:sweet_berries":9,"minecraft:oak_sapling":3,"alloy_forgery:polished_blackstone_forge_controller":2,"bewitchment:taglock":19,"minecraft:potato":2,"zenith:hellshelf":34,"minecraft:emerald_ore":9,"regions_unexplored:brimwood_leaves":1,"minecraft:diorite":48,"minecraft:leather_leggings":2,"minecraft:damaged_anvil":2,"regions_unexplored:redstone_bulb":1,"minecraft:stripped_birch_log":13,"minecraft:blackstone":3,"minecraft:leather_chestplate":2,"create_new_age:overcharged_diamond_wire":2,"regions_unexplored:pointed_redstone":9,"zenith:filtering_shelf":2,"minecraft:sand":1,"bewitchment:aconite_seeds":5,"minecraft:lectern":15,"minecraft:diamond_ore":8,"minecraft:fire_charge":2,"bewitchment:brazier":1,"minecraft:diamond_sword":595,"minecraft:smithing_table":2,"minecraft:birch_log":16,"bewitchment:stone_witch_altar":10,"create_enchantment_industry:disenchanter":5,"minecraft:enchanting_table":5,"create:schematic_table":1,"create_new_age:generator_coil":3,"zenith:glowing_hellshelf":7,"minecraft:netherrack":505,"minecraft:torch":123,"minecraft:brewing_stand":5,"minecraft:anvil":2,"mythicmetals:bronze_pickaxe":706,"minecraft:twisting_vines":2,"bewitchment:witch_cauldron":10,"mythicmetals:bronze_axe":144,"design_decor:cardboard_box":11,"minecraft:iron_axe":199,"minecells:blood_sword":3,"create_new_age:energiser_t2":2,"minecraft:barrel":2,"minecraft:bamboo":1,"minecraft:basalt":9,"extended_drawers:t2_upgrade":6,"create:fluid_pipe":29,"minecraft:cobbled_deepslate":12,"create:belt_connector":2,"minecraft:wheat_seeds":10,"minecraft:water_bucket":2,"create_dd:potassic":57,"extended_drawers:single_drawer":27,"farmersdelight:tomato_crate":1,"minecraft:birch_planks":27,"minecraft:bundle":2,"minecells:elevator_assembler":10,"minecraft:leather_boots":2,"minecraft:gold_ore":15,"minecraft:polished_blackstone_bricks":6,"regions_unexplored:tsubaki":1,"minecraft:mossy_cobblestone":10,"minecraft:crafting_table":10,"minecraft:red_bed":1,"minecraft:white_bed":15,"bewitchment:dragons_blood_sapling":1,"minecraft:spruce_log":78,"minecraft:oak_log":42,"minecraft:diamond_pickaxe":9650,"minecraft:iron_pickaxe":516,"mythicmetals:bronze_boots":2,"mythicmetals:midas_gold_sword":336,"regions_unexplored:brimsprout_nylium":1,"create:mechanical_arm":3,"minecraft:spruce_sapling":30,"minecraft:enchanted_book":15,"minecraft:cobblestone":957,"minecraft:potion":4,"bountiful:bountyboard":1,"travelersbackpack:standard":7,"zenith:infused_hellshelf":5,"regions_unexplored:glistering_fern":1,"minecraft:cooked_porkchop":32,"bewitchment:cypress_sapling":9,"minecraft:kelp":7,"minecraft:stripped_oak_log":31,"minecraft:candle":4,"create:clutch":1,"minecraft:brush":6,"minecraft:jukebox":3,"minecraft:moss_carpet":1,"zenith:treasure_shelf":1,"minecraft:blue_terracotta":1,"minecraft:shield":14,"regions_unexplored:glistering_sprout":10,"create:cogwheel":13,"minecraft:nether_bricks":3,"bewitchment:elder_log":4,"minecraft:tuff":2,"minecraft:obsidian":18,"mythicmetals:bronze_leggings":2,"farmersdelight:roast_chicken":16,"minecraft:milk_bucket":5,"create_new_age:fluxuated_magnetite":10,"minecraft:coal_ore":6,"minecraft:lantern":9,"minecraft:packed_mud":1,"bewitchment:white_coffin":4,"bewitchment:juniper_log":8,"minecraft:item_frame":2,"minecraft:magma_block":18,"bewitchment:golden_chalk":2,"culturaldelights:glow_squid":1,"bewitchment:garlic":4,"bewitchment:athame":128,"zenith:seashelf":28,"minecraft:stone_pickaxe":374,"minecraft:ender_pearl":5,"minecraft:sugar_cane":27,"travelersbackpack:iron_golem":11,"minecraft:diamond_axe":220,"create:mechanical_saw":3,"regions_unexplored:dorcel":1,"regions_unexplored:cobalt_obsidian":4,"bewitchment:waystone":6,"minecraft:shears":6,"minecraft:lever":2,"minecraft:dark_oak_log":1,"minecraft:bread":69,"create_new_age:copper_wire":8,"create_new_age:energiser_t3":1,"nethersdelight:hoglin_sirloin":29,"create_new_age:electrical_connector":6,"regions_unexplored:cobalt_roots":2,"minecraft:andesite":3,"minecraft:grindstone":1,"create:vertical_gearbox":3,"minecraft:coarse_dirt":6,"minecraft:chain":177,"minecraft:bone_meal":104,"minecraft:air":3,"minecraft:cobweb":3,"create:large_cogwheel":2,"minecraft:flint_and_steel":5,"minecraft:redstone_ore":12,"minecraft:stone_shovel":17,"minecraft:dried_kelp":137,"immersive_weathering:soot":8,"minecraft:spruce_planks":6,"bewitchment:mandrake_seeds":10,"bewitchment:spruce_poppet_shelf":3,"minecraft:stone_hoe":24,"minecraft:dirt":58,"create:mechanical_pump":9,"minecraft:hopper":2,"minecraft:golden_chestplate":1,"minecraft:granite":13,"minecraft:dark_oak_planks":2,"minecraft:wooden_axe":12,"bewitchment:cypress_log":2,"regions_unexplored:glistering_wart":2,"minecraft:bookshelf":33,"regions_unexplored:glistering_nylium":1,"minecraft:golden_carrot":7,"regions_unexplored:blue_lupine":1,"nethersdelight:hoglin_loin":6,"minecraft:cooked_mutton":5,"minecraft:iron_ore":3,"botanypots:terracotta_hopper_botany_pot":4,"bewitchment:juniper_sapling":8,"farmersdelight:skillet":2,"minecraft:glass_bottle":20,"minecraft:baked_potato":56,"minecraft:mud_brick_slab":1,"minecraft:red_nether_bricks":2,"regions_unexplored:peat_dirt":15,"create_new_age:energiser_t1":4,"extended_drawers:t1_upgrade":1,"create:item_drain":3,"regions_unexplored:brimsprout":3,"immersive_weathering:spruce_bark":4,"minecraft:book":3,"create_new_age:layered_magnet":10,"bewitchment:belladonna_seeds":2,"minecraft:flower_pot":1,"minecraft:apple":71,"mythicmetals:bronze_chestplate":2,"mythicmetals:bronze_sword":366,"minecraft:lapis_ore":4,"beautify:bookstack":9,"bewitchment:chalk":60,"bewitchment:juniper_broom":162,"minecraft:bucket":8,"create:hand_crank":2,"minecraft:pumpkin_pie":17,"regions_unexplored:maple_log":1,"minecraft:splash_potion":1}},"DataVersion":3465}